{
  "key": "uber",
  "label": "Uber",
  "defaultIconStyle": "emoji",
  "telescopeCssVariables": {
    "--brand-tbd-base": "#ffffff",
    "--brand-tbd-dark": "#e5e7eb",
    "--feature-base": "#e14327",
    "--text-normal-primary": "#ffffff",
    "--text-normal-secondary": "#bcbcbc",
    "--background-normal-primary": "#121212",
    "--background-normal-secondary": "transparent",
    "--background-normal-tertiary": "#242424"
  },
  "sdkCssVariables": {
    "--font-family": "system-ui, sans-serif",
    "--sdk-roundness-card": "0px",
    "--sdk-category-card-bg": "transparent",
    "--sdk-category-card-border": "transparent",
    "--sdk-category-card-icon-bg": "#242424",
    "--sdk-category-card-icon-border": "transparent",
    "--sdk-category-card-icon-container-size": "76px",
    "--sdk-category-card-icon-container-radius": "9999px"
  }
}
